epiweeks/__init__.py
epiweeks/py.typed
epiweeks-2.3.0.dist-info/LICENSE
epiweeks-2.3.0.dist-info/METADATA
epiweeks-2.3.0.dist-info/WHEEL
epiweeks-2.3.0.dist-info/top_level.txt
epiweeks-2.3.0.dist-info/RECORD
