Metadata-Version: 2.1
Name: epiweeks
Version: 2.3.0
Summary: Epidemiological weeks calculation based on the US CDC (MMWR) and ISO week numbering systems
Home-page: https://github.com/dralshehri/epiweeks
Author: Mohammed Alshehri
Author-email: 
License: MIT
Project-URL: Documentation, https://epiweeks.readthedocs.io
Project-URL: Source Code, https://github.com/dralshehri/epiweeks
Keywords: epidemiology,weeks,cdc,mmwr,iso,calendar,surveillance,public-health
Classifier: Development Status :: 5 - Production/Stable
Classifier: Intended Audience :: Developers
Classifier: Intended Audience :: Science/Research
Classifier: Intended Audience :: Healthcare Industry
Classifier: License :: OSI Approved :: MIT License
Classifier: Natural Language :: English
Classifier: Operating System :: OS Independent
Classifier: Programming Language :: Python
Classifier: Programming Language :: Python :: 3
Classifier: Programming Language :: Python :: 3.8
Classifier: Programming Language :: Python :: 3.9
Classifier: Programming Language :: Python :: 3.10
Classifier: Programming Language :: Python :: 3.11
Classifier: Programming Language :: Python :: 3.12
Classifier: Topic :: Scientific/Engineering
Classifier: Topic :: Utilities
Classifier: Typing :: Typed
Requires-Python: >=3.8
License-File: LICENSE
